tfsp/__init__.py
tfsp/__main__.py
tfsp/_version.py
tfsp/tag_from_spotify.py
tag_from_spotify-0.4.1.dist-info/LICENSE
tag_from_spotify-0.4.1.dist-info/METADATA
tag_from_spotify-0.4.1.dist-info/WHEEL
tag_from_spotify-0.4.1.dist-info/entry_points.txt
tag_from_spotify-0.4.1.dist-info/top_level.txt
tag_from_spotify-0.4.1.dist-info/RECORD
