Metadata-Version: 2.1
Name: tag-from-spotify
Version: 0.4.1
Summary: fetch audio metadata from spotify and tag them to your audio files
Home-page: https://github.com/Detsudetsu/tag-from-spotify
Author: Detsu
Classifier: Programming Language :: Python :: 3
Classifier: License :: OSI Approved :: GNU General Public License v3 or later (GPLv3+)
Classifier: Operating System :: OS Independent
Requires-Python: >=3.6
License-File: LICENSE
Requires-Dist: spotipy
Requires-Dist: mutagen
Requires-Dist: tqdm
Requires-Dist: click
Requires-Dist: fire
Requires-Dist: python-dotenv
